<?xml version="1.0" encoding="UTF-8" standalone="no"?>
<!-- saved from url=(0014)about:internet -->
<pk><wd nm="meschool" rd="550,0:316245"/><wd nm="meservice" rd="550,0:353416,361184"/><wd nm="mesets" rd="6,0:802,926"/><wd nm="mespace" rd="51,0:5233|224,0:453,528|540,0:64,1009,5674,5809,6206,6343,6728,6871,7248,7379,7788,7931,8312,8445|541,0:54,979,8227,8359,8548,8672,8913,9047,9444,9586,9966,10095,10468,10598,10975,11107,11511,11652,12037,12173,12568,12709,13121,13266,13655,13793,14170,14302|542,0:62,987,3506,3633,4024,4159,4548,4686|543,0:61,986,6470,6597,6979,7114,7506,7642,8038,8180,8594,8741,9127,9264,9648,9780|544,0:60,985,4028,4154,4522,4650,5038,5172,5556,5692|545,0:65,990,4371,4502,4896,5043,5427,5561,5959,6108|546,0:62,1037|547,0:63,988,3638,3767,4163,4300,4692,4831|548,0:66,991,5335,5466,5623,5873,6010,6175,6429,6568,6725,6991,7136,7301,7575,7724,7881,8161,8321,8478|550,0:129350,129414,129520,365203"/><wd nm="mess" rd="550,0:144868"/><wd nm="message" rd="1,0:4095,4154,4195,4207,4315,4336|7,0:3253|24,0:1086,1222,1652|25,0:196,211,227,285,322,485,616,1402,2616,4454|26,4:322,770,809|27,0:883,937|30,0:449|31,0:726,1082,1428,1630|32,0:4102,4166,4362|33,0:452,2166,2868|34,0:819,2133,2409,3300,3677,4298|35,0:1484,1639|36,0:2125,4444|39,0:276,380,579,629,729,1173,1785,1880,1932,1975,2001,2074,2388,2509,2542,2652,2662,2676,2707,2870,2892,2903|41,0:440,482,910,1152,1670,1748,1926,1941,1956,1984,2183|42,0:1030,1295|43,0:1008|44,0:2045|46,0:214,737,960,1283,1314,1327,1374,1405|48,0:408,1098,1306,1572,1846,2121,2388,2653|50,0:1075,1142,1663,1791,1830,1900,2001|51,0:5047,5101,5942,6098,6137,6154,6198,6264,6305,6361,6455,6539,6570,7139,7200,7325,7585,7741,7780,7797,7841,7951,8017,8029,8055,8100,8156,9199,9223,9256,9322,9395,9468|52,4:5056,5265,5284|54,0:4499|65,0:34320,34383|136,2:102|146,0:1554|147,2:5,31,110,479,919|148,0:0,33,61|149,1:0,33,68,127,185|151,0:182,469,753,1024,1493|153,0:552,670,1071|157,0:997,1281,1326,1603,1646,1696,1784,1886,1971,2035,2212,2365,2487,2733,3064,3291,3305|158,1:37,735,783,886|159,1:27,144,1758|160,1:27,1605|161,0:424,484,689,724,767|162,1:25,745,1492,1518|166,0:793|170,0:174|184,0:6782,7058,7264,7357|185,0:1980,3094|187,0:331|192,0:3543,4453,4648,4686,4707,4760,4790,4835,5275|214,0:1041|218,0:711|222,0:905|224,0:590,6338,6544,17845,17879,17919|320,0:1644|337,0:1100|378,0:828|392,0:221|402,0:343|403,0:245,260,276,334,908,1123,1307,1438,1897,2001,2104,2207|406,0:279,897|407,0:869,914,982,1051,1129,1339,1835,1850,2125,2182|423,0:1438|424,4:8419,8435,8474,8787,8870,8982,9063,9143,9242,9301,9331,9439,9530,9615,9668,9741,9800,9860,9964,10016,10070,10120,10215,10342,10396,10467,10535,10555,11369,11733,13781|427,0:1112,1472,1927|439,0:932|442,0:680,2599,2614|444,0:11,39,62|445,8:547,558,570,1080,1139,1180,1192,1300,1321,3084,3146,3299,3338,3398,3482,3502,3560,3580,3616,3679,3711,3753,3809,3857,3871,4355,4422,4475,4515,4550,4576,4638,4703,4738,4817,5032,5120,5141,5163,5313,5462,5562,5628,5700,5733,5828,5849,5975|448,0:11,34,52|449,0:11,36,56|450,0:11,33,50|455,0:503|456,0:3,18,28|457,0:3|460,4:176,206,244,466,482,557,904,947,1305|476,0:858|535,0:7524|536,0:35033,35138,35167,35394,36436,42309|540,0:1078,1358,1370,1482,1502,1823,1835,1951,1963,2083,2095,2207,2219,2500,2512,2616,2628,2916,2928,3056,3068,3140,3152,3260,3429,3512,3588,3804,3883,3963,4120,4195,4271,4461,4528,4596,4814,4905,4997,5136,5207,5279|541,0:1068,1097,1109,1176,1188,1325,1337,1367,1379,1466,1478,1588,1618,1696,1708,1834,1846,1914,1926,2028,2040,2107,2119,2198,2210,2302,2314,2351,2363,2469,2481,2653,2665,2789,2801,3020,3041,3155,3167,3288,3300,3400,3412,3538,3550,3682,3694,3878,3890,4008,4020,4110,4122,4228,4340,4391,4481,4534,4654,4736,4810,4952,5041,5131,5265,5328,5392,5527,5592,5658,5772,5841,5911,6092,6179,6267,6440,6517,6604,6757,6844,6932,7094,7189,7285,7450,7531,7613,7755,7824,7894|542,0:1076,1298,1310,1406,1418,1673,1685,1797,1809,1993,2005,2123,2135,2227,2351,2410,2470,2646,2729,2805,2970,3051,3133|543,0:1118,1232,1244,1322,1334,1672,1684,1780,1792,2148,2160,2272,2284,2520,2532,2658,2670,2908,2920,3056,3068,3251,3263,3379,3391,3558,3570,3684,3696,3788,3939,3998,4058,4262,4337,4413,4555,4632,4710,4894,4991,5081,5275,5374,5474,5638,5717,5797,5953,6022,6092|544,0:1074,1172,1184,1252,1264,1533,1545,1637,1649,1743,1755,2043,2055,2165,2177,2359,2371,2485,2629,2686,2744,2876,2937,2999,3189,3262,3336,3499,3576,3654|545,0:1079,1382,1394,1498,1518,1610,1622,1946,1958,2068,2080,2182,2194,2314,2326,2545,2557,2689,2839,2906,2974,3173,3256,3340,3479,3552,3626,3798,3885,3973|546,0:2873,3035,4823,7707,7721,19784|547,0:1077,1169,1181,1281,1293,1560,1572,1688,1700,1983,1995,2180,2192,2312,2446,2509,2573,2766,2845,2925,3091,3174,3258|548,0:1123,1227,1239,1411,1423,1541,1553,1702,1714,1834,1846,2009,2021,2147,2159,2293,2305,2399,2411,2538,2550,2647,2659,2784,2796,2888,3022,3089,3157,3320,3399,3479,3652,3743,3827,3998,4093,4189,4347,4450,4554,4715,4824,4934|550,0:128960,129138,144882,267911,268085,269105,270915,273923,274066,385794,386334|553,0:597,2770"/><wd nm="message:message" rd="27,0:937"/><wd nm="message_only" rd="550,0:128580,128642,129079,129099"/><wd nm="message_statistics" rd="427,4:1082"/><wd nm="messageattributes" rd="553,0:611,2570"/><wd nm="messagecount" rd="424,0:9630|546,0:3075"/><wd nm="messagedaoimpl" rd="46,0:1010"/><wd nm="messagedigest" rd="550,0:278775"/><wd nm="messagefilter" rd="546,0:22627"/><wd nm="messagefilterid" rd="546,0:22667"/><wd nm="messageid" rd="25,0:2665,4503|424,0:9573|546,0:2910|553,0:2607"/><wd nm="messageids" rd="25,0:2189,2203,2378,2391,2552,4327,4340,4390"/><wd nm="messages" rd="1,0:4117,4271|18,0:770|25,0:155,2525,4363|26,0:996|30,0:992|31,0:1189,1210|33,0:888|34,4:764,950,1099,1248,1720,1863,1906,1947,2037,2377|36,0:2054,2090,4348,4792|39,0:205,241,360,1222|41,0:415,1657|43,0:193,325,376|46,0:1162,1213|48,0:194|50,0:435|52,0:4824,4961,5307,5392,5411|54,0:1749,1904,2268,2777,2912,3038,4157,4458,4891,5084|59,0:154|65,0:17989,18404,46793|66,0:6489|68,0:15508,15685|78,0:3907,3983,4195,4271,4481,4557,4770,4846,5059,5135|90,0:2862,2938,3119,3195,3375,3451,3634,3710,3893,3969|96,0:1450|106,0:2859,3039,3248,3409,3637,3719,4329,4488,4700,5116,5298,5504,5668,5891,5973,6609,6766,6974|123,0:3169,3218,3249,3285,3317|125,0:215|126,0:220|130,0:4157,4233,4464,4540,4769,4845,5077,5153,5385,5461|147,0:168,361,666|149,0:260,532|151,0:540,605,681,920,1542,1978,2122,2144|153,0:874,923,999,1468|154,0:2730|156,0:223,1292,1560|157,2:8,107,1064,1163,1436,1486,1572,2571,2809,2986,3207,3251|158,0:244,407,506,704,940,1052,1225,1279,1291,1413,1557,1732,1862,1955|159,0:352,487,585,604,796,1112,1309,1721,1891,1979|161,0:219,268,555,900,988,1514,1596,1884|162,0:188,242,480,557,619,722,790,904|166,0:385,516|184,0:210,5718|185,0:763,1235|187,0:239,568,631,654|192,0:2499,3256|203,0:1541|222,8:154,386,443,795,869|223,0:3930|224,0:679,2454,2609,4569,6256,6456,6743,6782,6891,6942,7030,7131,7184,7255,7336,7409,9280,13332,13765,14166,14232,14258,15727,17150,17183,17784,18020|225,0:831|227,0:1198|396,0:110|402,0:216,476,741,880|403,0:204,1740,1958,2062,2165,2268|406,0:490,670|407,0:348,926,1038,1286|410,0:966,1119|424,0:10975|427,0:1207,1518,1606,1738,1831,1973,2064|442,0:823,982|445,0:1102,1256,2580,3169,3270,4100,4798,5369,5397,5865|451,2:203,389,442,532,568,584,637,820,1275,1663|452,4:6,14,79|453,0:1833|454,0:466|455,0:291,353,457|460,0:338,380,635,1165,1252|529,0:909|533,0:1180|535,0:2060|536,0:12385,12610,12653,14682,16825,36162,36364,36504,36737,38624,39147,39238,40695,42523|550,0:386188|552,0:61263"/><wd nm="messages_en" rd="26,0:1032"/><wd nm="messages_jp" rd="26,0:1092"/><wd nm="messagescleanedpersec" rd="131,0:1264,1370"/><wd nm="messagesquarantinedpersec" rd="131,0:1501,1611"/><wd nm="messaging" rd="21,0:656"/><wd nm="mestamp" rd="69,0:8062|192,0:399,666|197,0:656,885|202,0:1975|218,0:2358,2633|219,0:1632,1938|220,0:1601,1873|221,0:2076|222,0:1706|223,0:2022|330,0:1971|536,0:42265"/><wd nm="mestamped" rd="36,0:4337|280,0:912"/><wd nm="met" rd="73,0:5961|237,0:1366|539,0:56353|549,0:4287"/><wd nm="meta" rd="32,0:904|44,0:2409,2447,2496|45,0:604|47,0:267|550,0:45724,61881,71307,80062,88360,99567,99841,99874,172871,182923,184711,187423,221692,225947,228585,242491,247952,257271,286190,314707,319046,323652,324775,326013,327560,327651,327881,329423,335456,335971,336438,345557,351370,352510,363948,366201,390730,415626,416713,416782,416832,416897,416918"/><wd nm="metadata" rd="32,4:1203,1235|41,0:2413|48,2:1,152|49,0:847|57,0:150|147,0:1006|219,0:2866|550,0:264435,339871,399083"/><wd nm="metadataservice" rd="550,0:267867,268040,268999,269049,270815,270862,271301,271382,271471,271557,271664,271850,271931,272013,272103,272155,272337"/><wd nm="metal" rd="223,0:520"/><wd nm="meter" rd="25,0:2107,2293,2414,4105,4135,4244|34,0:545|51,0:8448,8843|53,0:6414,6637,6909,7014|65,0:45642|66,0:8579,9117,9351,9686,9953,11879|95,0:224|118,0:12253|121,0:2315,2439,2574,2704|161,0:2267|253,0:194|258,0:1052|334,4:1135,1206,1271,1481,2117,2527,3119,3225|351,0:468|360,0:1320|406,0:880,1016|422,8:539,632,650,2169,2920,3028,3118,3160,3210,3234,4367,4525,4629,4671,4721,4745|427,0:474,949,1665,2118,2582,3677,3745,3813,4096,5339,5424,5492,5775|431,0:243,329,570|433,0:80,309,395,579,662|435,0:73,230,316,500,583|437,0:68,238,428,514,699,782|438,0:2667,4597,5719,6422|439,0:56,649,691,843,1107,1316|442,0:1422,1552,2664|460,0:1029,1387|474,0:2110,2806,3839,4748,5701|476,0:700|480,0:63|481,0:67|482,0:1141,1699,2986|510,0:2590,2755|535,0:2526,5133|536,0:11203,21926|539,0:37067|550,0:72155,72598,72638,73792,73832,74035,74539,74865,76172,120910,124117,149482,152891,153104,153548,153722,153908,154013,154448,158230,158418,164928,174256,175142,175179,175343,175615,176745|552,0:21729,21890,23231,59924"/><wd nm="meterorder" rd="540,0:3334,3697,4070,4374,4719,5102|541,0:4288,4626,4924,5232,5494,6024,6375,6717,7049,7395,7717|542,0:2291,2577,2915|543,0:3851,4165,4521,4824,5200,5583,5901|544,0:2554,2844,3105,3444|545,0:2760,3085,3446,3739|547,0:2379,2682,3036|548,0:2960,3266,3590,3944,4310,4678"/><wd nm="meters" rd="25,8:2038,2149,2273,2599,4039,4067,4437|51,0:8293|53,0:6383,6880,7141|54,0:735,940,1127,1986|65,0:9585,12824|66,0:8252,10680,11628|68,0:12214|69,0:5531,5667,6274,6392|73,4:3517,3570,3587,7794,7816,7865|74,4:1764,1817,1834,2071,2784,2806,2855|76,4:1693,1746,1763,2829,2851,2900|77,4:1849,2066,2083,2808,2830,2879|78,4:3637,3654,5415,5437,5486|79,4:1655,1672,2164,2186,2235|80,4:1795,1812,2352,2374,2423|81,4:1886,1903,2630,2652,2701|82,4:3587,3604,7234,7256,7305|83,4:2651,2668,4575,4597,4646|84,4:4543,4560,7355,7377,7426|85,4:1720,1737,2558,2580,2629|86,4:1739,1756,2569,2591,2640|88,4:1643,1660,2243,2265,2314|89,4:2593,2610,4028,4050,4099|90,4:2570,2623,2640,4130,4152,4201|91,4:3490,3543,3560,5287,5309,5358|93,4:2282,2335,2352,3727,3749,3798|97,4:2280,2333,2350,4937,4959,5008|99,4:1552,1605,1622,2125,2147,2196|100,4:1502,1555,1572,2070,2092,2141|101,4:1446,1499,1516,1962,1984,2033|102,4:2331,2958,2975,5363,5385,5434|103,4:1390,1443,1460,1763,1785,1834|104,4:3142,3195,3212,9307,9329,9378|105,4:2094,2147,2164,3288,3310,3359|106,4:2664,2717,2734,4887,4909,4958|107,4:2123,2176,2193,3464,3486,3535|108,4:402,2240,2293,2310,2659,2681,2730|110,4:1367,1420,1437,1703|111,4:3607,3660,3677,9336,9358,9407,9649,9859,10058,10247,10436|112,4:2217,2270,2287,3934,3956,4005|113,4:2039,2429,2446,3046,3068,3117|114,4:2012,2065,2082,2642,2664,2713|115,4:1909,1962,1979,2301,2323,2372|116,4:1986,2039,2056,2721,2743,2792|117,4:1889,1942,1959,2760,2782,2831|118,0:1075,1354|119,4:2296,2349,2366,2976,2998,3047|120,4:2025,2078,2095,2655,2677,2726|121,4:2123,2176,2193,2813,2835,2884,3416|123,4:2982,3035,3052,5067,5089,5138|124,4:2303,2356,2373,3729,3751,3800|127,4:1562,1615,1632|128,4:6039,6092,6109,7043,7065,7114|129,4:1951,2004,2021,2765,2787,2836|130,4:3815,3868,3885,5760,5782,5831|131,4:2818,2871,2888,3548,3570,3619|132,4:1825,1878,1895,2406,2428,2477|133,4:1847,1900,1917,2589,2611,2660|134,4:1939,1992,2009,2765,2787,2836|135,4:3575,3628,3645,7484,7506,7555|136,4:1924,1977,1994,2803,2825,2874|137,4:1657,1710,1727,2240,2262,2311|138,4:3673,3726,3743,6502,6524,6573|139,4:5745,5965,5982,9043|140,4:1878,1931,1948,2661,2683,2732|142,4:1805,1858,1875,2289,2311,2360|143,4:1796,1849,1866,2468,2490,2539|144,4:3153,3206,3223,4665,4687,4736|154,0:3139|184,0:9157|201,0:203,1159|222,0:2818|224,0:16229|233,0:3748|252,0:4836|258,0:2033|309,0:575|332,0:512,1516|334,128:12,157,372,421,3835|335,0:667|338,0:1067|350,0:1266|351,0:847,1197|396,0:55|404,0:562|406,0:658,961|417,0:445|422,0:619,3064,3276,3286,4571,4787,4797|427,8:356,896,909,1350,1363,2529,2542,3663,5222,5257|431,128:13,33,952|433,128:14,34,1045|435,128:17,37,969|437,128:12,32,1163|438,0:2654,4584,5706,6409|439,128:12,32,88,780,1585|442,0:1120,2651|445,0:684|453,0:1463|457,128:16,36,49,214|459,128:13,33,46,253|460,0:1016,1374|463,128:18,38,51,770|465,128:17,37,50,752|466,128:4,24,37,1057|467,128:5,25,38,1089|468,128:12,32,45,666|474,0:1744,2097,2312,2793,3086,3810,3826,4163,4719,4735,5103,5672,5688|476,0:760,790,1797|480,128:7,27,327|481,128:8,28,404|482,0:1686,2973|536,0:9940|539,0:41641,75718|546,0:24172|550,0:17077,75985,91823,115830,115925,120897,123981,128871,147553,149249,149312,149380,149658,149793,149839,149886,150021,150187,150308,150459,150522,164629,164694,164722,164817,165340,174132,174884,175563,176296,176312,176815,176831,181158|551,0:6594,35401|552,0:12640,22129,22980,64369,64506,65474,65592"/></pk>
