<?xml version="1.0" encoding="UTF-8" standalone="no"?>
<!-- saved from url=(0014)about:internet -->
<pk><wd nm="emember" rd="184,0:3800,3994,4178,4294|246,0:1189|383,0:800|451,0:767|539,0:18693|550,0:56190,208639,252350,276084,276505,288697"/><wd nm="emembered" rd="550,0:56572"/><wd nm="emembering" rd="187,0:440"/><wd nm="emembers" rd="550,0:241654,246211,246316"/><wd nm="emembership" rd="550,0:296296"/><wd nm="emembershipevaluationspersec" rd="128,0:4736,4839,4984,5084"/><wd nm="emembershipmoduleimpl" rd="550,0:8642,257516,297068,297366,297443,303589"/><wd nm="emename" rd="550,0:352558,353321,363996,390865,391728"/><wd nm="emendous" rd="536,0:6063"/><wd nm="ement" rd="1,0:2206,2282|6,0:493,561,590|24,0:1501,1517,1581,1592,1929,1940,2124,2135,2337,2348,2587,2598,2843,2857|25,0:4563|31,0:258,982,1497|34,0:1301,1328|36,0:259|44,0:1452,1639,1765,1880|45,0:474|50,0:2161|51,0:1981,2463,5527,8628|52,0:1593,1833,2131,2251,2687,2800|53,0:440,927,2259,5772|65,1:34,906,5260,15916,16096,17017,17429,18767,19124,23882,30553,39142,39879,39965|66,1:33,936,1910,2040,2091,17377,26646,26705|67,1:36,171|68,1:33,661,1662,8197,10213,18740,20110,24400,25613|69,1:39,622,9333,9428,10372,11272,11386|94,0:542|96,0:1523|102,0:5154|104,0:182|118,0:1774,1956,4108|127,0:189|128,0:227|129,0:214|130,0:207|131,0:220|132,0:226|133,0:218|134,0:227|135,0:217|136,0:222|137,0:183|138,0:198|140,0:211|141,0:180,639|142,0:184|143,0:192|144,0:185|146,0:7266|157,0:1823,2092,3165|158,0:2051|161,0:3359|163,0:193|165,0:224|166,0:208|167,4:170,205,236,276,376,493,1529|169,0:435|174,0:152|176,0:695|177,0:142|179,0:1046|180,0:538|183,0:673,702|184,0:2309|185,0:698,912,1114|187,0:162|188,0:302,453|202,0:3918|203,0:1280|204,0:264,283,379,442,456,707,785,801,898,1105|211,2:109,459,487|212,2:118,388,416|213,2:110,416,444|214,2:110,475,503|223,0:7763|224,0:1480,8514|228,0:2017|230,0:1609|233,0:6038|236,0:221|237,0:1493|238,0:151,218|241,0:519,545,1606|248,0:1032|250,0:906,3160|254,0:1611|256,0:176,940|259,0:270|261,0:388,947|280,0:513,638|308,0:489,3845|317,0:1201|324,0:402,1432|350,0:143|351,0:149|377,0:262|384,0:243|407,0:367|422,0:5434,5541|425,0:2137,2351|453,0:929,1151|474,0:3154,3290,4375,5320|483,0:258,351,578,1433|486,0:366,1106|494,0:515,1285|502,0:667,757|510,0:480,624,1257,1401,2337,2481,2564,2729|514,0:216|515,0:4511|529,0:1191|533,0:1462|534,0:1006|535,0:1687,1966,2398,3920,6426,6782|536,0:744,941,2444,3559,5415,8261,17939,19753,20437,27106,34123,34859,42297|539,0:2160,3900,6184,21171,31524,34115,34843,47996,53470,53496,54557,56480,57437,59526,59593,78012|541,0:2265|542,0:2190|543,0:3751|544,0:1600|545,0:1573|546,0:1155,1188,1289,1322,1429,1462,1578,1629,1662,1764,1797,1906,1939,2046,2079,2185,2218,2322,2355,2457,2495,2602,2635,2675,2724,2895,2933,2976,3020,3060,3098,3144,3189,3230,3270,3324,3382,3426,3470,3516,3560,3608,3774,3812,3867,4045,4086,4129,4169,4205,4259,4303,4347,4393,4432,4467,4513,4559,4625,4750,4808,4844,4920,4966,4998,5041,5081,5114,5168,5224,5398,5434,5478,5541,5672,5756,5842,5922,6006,6092,6172,6320,6358,6391,7248,7306,7354,7394,7427,7467,7519,7646,7692,7768,7844,7926,8008,8076,8140,8214,8296,8391,8495,8587,8697,8769,8851,8927,9019,9113,9181,20201,20244,20277,20383,20419,20452,20559,20596,20629,20735,20767,20800,20916,20952,20985,21096,21137,21170,21277,21314,21347,21454,21491,21524,21631,21668,21711,21755,21788,21828,21964,22007,22051,22088,22130,22162,22273,22307,22340,22462,22511,22544,22652,22693,22726,22768,22894,22927,23032,23065,23169,23212,23245,23366,23407,23454,23502,23552,23684,23721,23754,23858,23892,23925,23965,24123,24157,24307,24341,24380,25464,25540,25618,25690,25766,25844,25916,26020,26084,26171,26307,26370,26493|547,0:1132|548,0:2851|549,0:2256,2737,4256,5299,5466,5500,5640,5658,6543|550,0:3510,6322,6722,6747,15814,17506,17738,19481,22714,22757,24959,30887,39724,42224,48282,60327,61586,62937,63041,63293,64774,67235,67481,81770,81884,82168,90016,90130,90382,91642,95708,96376,96434,96735,96794,96934,97047,97226,97872,97945,97997,98033,98111,98186,98273,98351,98400,98461,98716,98792,98839,98927,99320,99534,99716,99761,99769,99800,99834,99878,99886,100057,100430,100470,100537,100579,100653,100691,101056,101099,101140,101187,101220,101228,101262,101571,101707,101933,101979,102004,102300,102442,102480,102603,102645,102694,102733,102810,102876,102899,102930,102996,103346,103421,103478,103516,103773,103848,103887,103921,104264,104307,104348,104423,104490,104581,104682,105249,105285,105489,105557,105882,105916,106190,106479,106552,106912,106950,107192,107344,107416,107683,107759,107832,108135,108169,108559,108618,108804,108847,109087,109136,109191,109271,109330,109412,109605,109821,109886,109940,110002,110106,110151,110412,110459,110487,110512,110578,110928,111003,111062,111100,111390,111432,111475,111509,111833,111847,111974,112123,112297,113396,113521,113562,113658,113967,114171,114239,114448,114485,114514,114594,114981,115036,115102,115488,116976,117101,117158,117187,117230,117306,117691,117869,118224,118301,118505,118639,119435,119916,119926,120219,120229,122778,123383,123468,123500,123592,123681,123781,123951,124336,124405,124529,124887,125020,125142,131207,131357,131511,131841,132045,132113,132408,132515,132552,132581,132650,133058,133113,133179,133239,133412,133440,133477,133598,133972,134437,134500,145026,145096,145134,145409,145869,154187,154994,164056,166272,171667,172285,172305,172374,193412,195367,195616,196019,196046,196763,197034,197183,198374,198817,202518,202934,205519,205808,205881,206244,207267,208195,208360,208593,209517,209591,210267,210346,211451,222743,224977,237110,237201,237239,238832,239783,240058,242208,243616,245534,247247,249335,250601,252454,253458,254614,255470,256077,258099,259930,260693,260892,261002,261800,263347,263534,265493,266068,266367,267257,269333,269587,278573,278666,285869,295995,298777,309462,309638,314465,321056,331582,331641,331661,331733,334030,334089,334109,334181,334479,334538,334558,334630,334650,334712,339491,341644,342397,343248,343738,371594,382911,383542,395115,397747,398437,399805,401183,401233,401422,401508,401603,402064,402508,402735,402931,403071,403414,403587,403748,403798,404003,404069,404269,404384,404452,404481,404532,404989,405164,405327,405657,405725,405780,405837,405909,406022,406094,406178,406246,406300,406340,406369,406412,406697,406764,406825,406895,407069,407108,407172,407210,407312,408317,408360,408430,408440,408489,408770,408806,409333,409459,409527,409556,409617,409692,409771,409855,409915,410003,410083,410118,410161,410446,410513,410579,410651,410929,410968,411030,411066,411204,412263,412529,412730,413397,413507,413619,413910,413979,414003,414065,414187,414407,414658,414688,414747,414975,415046,415070,415240,415410,415593,415654,416137,416147,416619,416662,416901,416911,417396,417522,417611,417815|551,0:651,693,1012,5333,7023,7255,9062,16681,21065,21583,21826,21905,22534,22820,22896,23015,23797,24517,24986,25781,25937,27844,28219,28395,29148,30272,30875,31019,31253,31631,31841,31982,32220,32833,33178,34131,35313,35882,35944,36039,36616,36951,37893,38685,38940,40116,41240,41400,41542,42249,42839,43379,43561,43780,43883,43959,44050,44500,44524,45221,45706,45835,45858,46055,46084,46140,46843|552,0:42,186,809,997,1998,3349,5188,6505,7457,8579,10595,11295,14756,15807,16624,16871,16911,17162,17823,19158,19409,19532,19575,19948,20729,21699,21933,24894,27703,30018,30787,31056,31200,31363,31688,31954,32076,33598,36443,36642,37482,39533,39684,40394,41443,41682,42705,42802,43300,43556,43735,43774,44288,44973,45722,47904,49840,52948,53432,53528,54223,54864,54991,55728,55814,57978,58787,61450,61662,62170,64872,65781,66623,66784,67001,67394,67841,68632|553,0:93,142,191,256,331,400,483,582,659,1044,1188,1711,1953,2009,2304"/><wd nm="ementaing" rd="550,0:257378,257459,257546,257640"/><wd nm="emental" rd="231,0:4053|539,0:52747"/><wd nm="ementation" rd="34,0:3773|36,0:2173,2862|41,1:45|42,1:46|43,1:47|44,1:48|45,1:51|46,1:48|47,1:45|48,1:47|49,2:124|50,1:44|51,0:2696|52,0:2362|73,4:3448,9848|74,4:1695,3458|76,4:1624,3351|77,4:1780,3144|78,4:3616,6135|79,4:1634,2395|80,4:1774,2593|81,4:1865,2967|82,4:3566,8796|83,4:2630,5692|84,4:4522,9471|85,4:1699,2885|86,4:1718,2896|88,4:1622,2474|89,4:2572,4610|90,4:2501,4870|91,4:3421,6786|93,4:2213,4332|97,4:2211,5834|99,4:1483,2461|100,4:1433,2407|101,4:1377,2205|102,4:2262,6893|103,4:1321,2001|104,4:3073,10959|105,4:2025,3909|106,4:2595,7137|107,4:2054,4192|108,4:2171,3067|110,4:1298,1717|111,4:309,3507,3538,10742|112,4:2148,5666|113,4:1970,3470|114,4:1943,3129|115,4:1840,2647|116,4:1917,3164|117,4:1820,3109|119,4:2227,3622|120,4:1956,3142|121,4:2030,2054,3389|123,4:2913,6151|124,4:2234,4451|125,4:1465,1924|127,4:1493,1834|128,4:5970,7181|129,4:1882,3101|130,4:3746,6475|131,4:2749,3686|132,4:1756,2637|133,4:1778,2830|134,4:1870,3102|135,4:3506,9017|136,4:1855,3124|137,4:1588,2483|138,4:3604,8011|139,4:5676,10076|140,4:1809,2988|142,4:1736,2427|143,4:1727,2696|144,4:3084,5333|154,0:153|183,0:164|222,0:4062|261,0:2463,2713|308,0:341,5175|531,0:428|549,0:653|550,0:1870,7138,17813,20751,48140,48245,60399,60636,61011,74366,79385,79506,84034,87592,89747,151628,166477,169837,193833,219400,220810,221795,232806,238137,238251,238303,238346,238431,250762,250778,251151,251592,252173,252189,252252,253911,253935,255982,257048,257926,258355,258595,258619,259138,259225,259354,276886,277866,278146,290096,290713,290944,290962,292237,292497,292515,293394,293625,293643,294117,294424,294442,296102,296682,296700,297303,297321,297806,297948,297972,298142,298158,298286,298304,300600,300618,300662,300680,300754,300772,300823,300847,300993,301009,301137,301155,303396,303414,303458,303476,303526,303544,303665,303689,303835,303851,304003,304021,308349,323474,335681,359036,367102|551,0:7330,10284"/><wd nm="ementations" rd="52,0:2646|550,0:7029,166777,237377,237627,247556,251219,251321,253730,256665,256699,256829,259961,260121,276481,276760,286114,290520,293201,295870,296221,299288,355210,359137"/><wd nm="ementbyid" rd="550,0:361887,361925,362025,397540"/><wd nm="emented" rd="35,0:342|36,0:2788,3172|39,0:2718|44,0:1399|47,0:411|51,0:3535,8727,9140|65,0:2425|66,0:2484,9245|68,0:9427|69,0:2340|102,0:3376|151,0:1076|184,0:3302|256,0:875|258,0:793|308,0:627|309,0:198|536,0:1303|539,0:34778|549,0:2419,3214|550,0:48388,60954,211222,232896,258375,295829,341548,341584,342791,342879,365393,372707,390258|552,0:9809,37234"/></pk>
