<?xml version="1.0" encoding="UTF-8" standalone="no"?>
<!-- saved from url=(0014)about:internet -->
<pk><wd nm="sensor" rd="32,0:522,801,4178"/><wd nm="sensor_1" rd="32,0:2275,4002,4513"/><wd nm="sensor_10" rd="32,0:3463,5312"/><wd nm="sensor_2" rd="32,0:2407,4602"/><wd nm="sensor_3" rd="32,0:2539,4694"/><wd nm="sensor_4" rd="32,0:2671,4781"/><wd nm="sensor_5" rd="32,0:2803,4868"/><wd nm="sensor_6" rd="32,0:2935,4957"/><wd nm="sensor_7" rd="32,0:3067,5044"/><wd nm="sensor_8" rd="32,0:3199,5133"/><wd nm="sensor_9" rd="32,0:3331,5220"/><wd nm="sensors" rd="31,0:1707|32,0:372,606,655,4338|36,0:582|536,0:9145"/><wd nm="sent" rd="18,0:374|30,0:358|31,0:304|32,0:530,683,3829,4353|34,0:702,2682,2886|36,0:1163|42,0:357|44,0:1724|52,0:4832|65,0:992,18417,35888|66,0:1020,19567|68,0:747,7292,17643,17772,21160,23405,23572,26452|69,0:725,4820,9030,10860,11869,11929,13368|82,0:812,831,918,4019,4099,4241,4310,7508,7561,7618,7686|102,0:3873,5968|104,0:1007,1086,4476,4528,4684,9776,9818,9907|106,0:3055,3735,4716,5314,5989,6006,6990|135,0:951,969,1050,4079,4153,4320,4389,7757,7809,7937|146,0:1436,1468|147,0:434|157,0:1297|184,0:10789,12037,12377|224,0:6499,14177,17022|226,0:643|231,0:496,1162,3125,3910|250,0:4106|254,0:2310|278,0:763,1759,1919|289,0:613,726|291,0:1820,1918,2206,2288|292,0:844|293,0:782,2996,3131,3446,3537|303,0:1583,1674,1740,2097|309,0:4196|324,0:768,1158,1870,3728,3975,4049,4220|325,0:237,303|330,0:1370,1744|368,0:331|417,0:1201|438,0:416,573|442,0:460,2784|460,0:665|474,0:705,841,1868,2573,3017,4098,5032|482,0:602|486,0:577|494,0:726|515,0:3667,3982|517,0:2951,3088,3210,3268,3472,3711,3839,3897,6582,6798,7043,7135,7331,7543,7667,8730,8860,8917,9107,9462,9661,12106,12314,12572,12670,12764,12894,13059|521,0:625|527,0:469|535,0:925,3382,6084|536,0:26956,44876|537,0:1256|539,0:7130,32291,49122,49788,51751,52604|550,0:49449,51117,52363,97440,99141,99642,101841,103829,106348,111413,114748,117393,132792,133326,134418,139891,140289,140673,161444,161892,162094,167451,207107,231384,259478,263484,263867,278315,278344,308217,341014,351349,390021,391763,402798,407131,408553,408999,409747,410991,412782,413147,414157,415517|551,0:14792,40827,44212|552,0:1083,7674,17511,17641,18718,61765,63856,67462,68293,68353,69499"/><wd nm="sentation" rd="51,4:4604,4785|66,0:26189|228,0:542|229,0:53,200|279,0:838|379,0:641,819,1205|438,0:656,1939,3875,5261,6345|460,0:319|523,0:1258|528,0:806|535,0:1264,1308,1347,1815|536,0:2624,5717,16395,17899,26826,35084,38352,41148|550,0:16913,106392,191913,192212,192330,355347,368264,368349,369510,398270,399931,402844|551,0:6430"/><wd nm="sentative" rd="549,0:7535"/><wd nm="sented" rd="27,0:160|52,0:6796|65,0:5313,22383|66,0:4779,5689,23250,23297,23607,24805,25380,26341,29419,29466,29756,30655|68,0:4425,4528,5946,6049,12881|69,0:6887,8386,9476,11434|146,0:3302|218,0:506|236,0:1816|239,0:640|243,0:428|244,0:418|249,0:3717,4433|251,0:812,1170,1679|330,0:1239|338,0:1953|377,0:1209|411,0:362|431,0:117,141|433,0:164,194|435,0:147,171|437,0:142,166,323,350|439,0:214,1078,1288,1401|442,0:1579|480,0:131|482,0:1929,2448|519,0:801|527,0:321,423|535,0:1504|539,0:17118,27144,27860,43272,44170,44498,45047,59032,78854|551,0:15251,36188,42109|552,0:4805,4908,6312,6415,13307,20842,31446,31846,31885,39586,44521"/><wd nm="sential" rd="223,0:934|225,0:361"/><wd nm="sentially" rd="65,0:8105,32814|66,0:6228,17157|68,0:8918|69,0:8445|236,0:651|536,0:21590,30250,33473,37038,39449,42744|539,0:57867|552,0:9300,28699"/><wd nm="senting" rd="104,0:302|231,0:709|460,0:542,1126|482,0:524|520,0:326|539,0:49335|550,0:276187,374094"/><wd nm="sently" rd="146,0:1275"/><wd nm="sentpermin" rd="106,0:1744,4659,6927,7112"/><wd nm="sents" rd="31,0:989|34,0:1335|36,0:3890,4017,4190,4259|64,0:469,726|66,0:24152,30237|68,0:21179,25697|118,0:6156|146,0:5362|183,0:470|185,0:2328|223,0:5351|252,0:1561|289,0:1780|424,0:3724,4201,4495,7066,10930,11338,11708,12046,13756|438,0:1049,2911,4911,5980|474,0:2978|482,0:899|522,0:1622,2512|536,0:17537,20725|539,0:36683|550,0:102518,106746,107987,108365,117729,141755,143029,144545,164399,164443,164493,199800,233510,233762,237718,238484,273149,403135,404129,404593|551,0:11669,44470"/><wd nm="sentwith" rd="552,0:31581"/><wd nm="separate" rd="36,0:3373,4917|41,0:316|51,0:4741|65,0:2495,3603,4041,26329|66,0:2554,3656,4091,10935,17673|68,0:3369,3894|69,0:2410,5405|156,0:731|184,0:5674|223,0:2340|230,0:1015|234,0:943,3170|241,0:511,1598|248,0:2428,3144|249,0:2451|250,0:507,3676|257,0:1786|289,0:1630|309,0:1395|329,0:823,1307|454,0:495|455,0:469|515,0:422,3395|524,0:1886|536,0:5950,15721,43991,44721|539,0:3501,6700,22570,23286,25878,47402,53462,54549,68074,70371|550,0:16882,18467,105408,114090,115874,131964,185718,360623,402244|551,0:6399,7984|552,0:3749,4274,20319,22384,30253,37304,38255,38622,47589,64243"/><wd nm="separated" rd="2,0:336|25,0:2223|39,0:564|42,0:1476|47,0:467|65,0:42165|66,0:12611,13543,14611,15426,16586,32459|108,0:3155|146,0:582,1292|231,0:926,2384,3565|246,0:2396,2602|249,0:3115,3521|291,0:1283|333,0:2468|338,0:316|476,0:1988|539,0:19901,20107,26542,26948,49552,51010,52191|550,0:338019|552,0:23906,25041,26045,26843,28128,33118,58067"/><wd nm="separately" rd="65,0:2268,28858|66,0:2329,11041|68,0:2185,10340|69,0:2173,5122|224,0:16699|228,0:1292|250,0:2751|252,0:2360|308,0:1769|425,0:1022|531,0:2800|536,0:7814,14825,17658,21245,37970|539,0:1435,5775,39139|549,0:7386|550,0:194498,249792,312036|552,0:2521,10722,22490,49633,64775"/><wd nm="separation" rd="550,0:343363,360114,368233,369274"/><wd nm="separator" rd="231,0:2570,2895|233,0:314|234,0:645|539,0:51196,51521,67776,72270|550,0:388476,388491"/><wd nm="separators" rd="536,0:35784"/><wd nm="sequence" rd="118,0:4457|145,0:1210|151,0:945|223,0:4849|225,0:265|231,0:966,1896|233,0:292,1880,3109|237,0:2070|539,0:49592,50522,57057,72248,73840,75043|546,0:1143,1219,1277,1354,1417,1494,1566,1694,1752,1833,1894,1974,2034,2113,2173,2252,2310,2387,2445,2529,2590,2712,2815,2827,2883,3596,3694,3706,3762,3855,3953,3965,4024,4613,4711,4723,4954,5212,5310,5322,5386,5595,5660,6252,6308,6431,7236,7566,7634,9271,20189,20317,20371,20492,20547,20669,20723,20850,20904,21025,21084,21210,21265,21387,21442,21564,21619,21893,21952,22199,22261,22383,22450,22581,22640,22826,22882,22961,23020,23096,23157,23285,23354,23603,23672,23794,23846,24052,24111,24237,24295,24420,25432,26008,26149,26241,26295,26431,26481,26565|553,0:130,179,730,1055,1699,1758,1941,2066,2292,2355"/><wd nm="sequences" rd="234,0:3570|539,0:70771"/><wd nm="sequent" rd="118,0:3822,8093|234,0:3816|249,0:2295,5159,5306,5453|308,0:6841|324,0:3946|338,0:1834|539,0:25722,28654,28801,28948,71017|550,0:173961,204478,337530,337644"/><wd nm="sequentially" rd="248,0:1309|539,0:21448"/><wd nm="sequently" rd="65,0:10456|68,0:20935|102,0:2651|145,0:1644|158,0:1692|248,0:490|249,0:444|250,0:953|252,0:1011|254,0:286|536,0:4418,10668,20454,30096,37689|539,0:3947,20607,23773,30199,36145|550,0:169100|552,0:16939"/><wd nm="ser" rd="1,0:520,538,935,1632,1650,3776,3979,4167|6,0:867,1018|7,0:1807,3318,3412|13,0:425|18,0:393,754|25,0:1768,2250|33,0:2903|34,4:1923|36,0:4776|38,0:1385|39,0:510|50,0:634,957|51,4:3750,4001,6501,7250,8397,9290,9306,9574|52,4:2127,2683,3373,3866,3964,4069,4261,4674,4692,5022,5826,5946|53,0:190,234,3138,3379,3468,3539,5722,5933,7211,7279|54,0:2063,2585,2616,4590|65,8:235,253,1159,1552,3226,3611,3748,3980,4167,4268,4351,4381,4433,4558,4599,4891,4928,4965,5011,5134,5152,5234,5256,5361,5394,5402,5422,5620,5627,5749,5789,6134,6252,6324,6350,6814,6889,6959,7087,7230,7370,7436,7619,8002,14842,15008,15295,15912,16051,16092,16157,16910,17013,17078,17328,17425,17490,18652,18763,18828,19058,19120,19185,20409,20629,20753,20945,21302,26788,26895,27248,27652,31915,34260,39517,39723,45959|66,8:230,248,3284,3664,3800,4031,4216,4316,4398,4427,4478,4602,4637,4706,4827,4864,4876,4893,4933,5035,5064,5416,5457,5544,5617,5748,5779,5796,5904,5946,6059,6085,6714,7307,7396,10418,10598,10827,18841,19606,20544,24272,30350|68,8:239,257,3004,3377,3506,3834,4019,4119,4146,4576,4642,4666,4709,4821,4838,4890,4913,4941,4967,5035,5061,5314,5451,5507,5604,5822,6784,6807,7003|69,4:260,1199,1952,3146,3545,3754,9745,9806,10017,10321,10512,12269,12632,12693,12901,13085|73,0:5165,5215|74,0:2018,2148,2258|84,0:3375,3417|95,0:200|97,0:6110|102,0:2423,2754,2845|104,0:3836,3904,4346,4414,4844,4912,5328,5396,5997,6065,6694,6762,7334,7402,7994,8062,8658,8726,9158,9226|118,0:340,2854,3938,4002,4097,4218,4549,4718,4756,5273,5473,5492,5540,5601,5737,5973,6069,6126,6389,6512,8071,9291,9703,9879,9925,10691,11285,11963|121,0:2377,2501,2636,2766|125,0:1920|127,0:674,716,924,1715,1794|138,0:2733,2773|139,0:5895,7790|145,0:212,235,374,756,982,1244,1290,2382,2438,2510,2545,2603,2904|157,0:1096|167,0:1035|172,0:324|173,0:749,773|183,0:643|189,0:439|192,0:299,445,687,1020,1806,2651,2773,4603,4672,4676,5048|195,0:294|196,128:22,157,366,472,601,637,1202|198,0:623|200,0:279,716|202,0:232,1162,3952|203,0:344,1268,2673|204,0:260,438,453,495,514,736,767,1173|205,4:161,1020,1038,1101,1132,1258,1315,1348,1411,1605,1626,1670,1683,1918,1971|206,0:577|207,128:7,30,48,166|211,0:135,239,455,483,555,730,867,1027,1055,1118,1130|212,0:384,412,484,659,796,956,984,1047,1059|213,128:8,106,126,230,275,297,412,440,512,687,824,984,1012,1075,1087,1313|214,128:8,106,137,202,241,253,336,356,471,499,736,763,809,911,927,982,1162,1215,1263,1422|215,128:8,34,54,173|216,128:8,33,53,173|218,4:325,1343|219,0:901|220,0:730|221,0:981|222,0:3299,3689|223,0:1145,2155,2483,2589,2701|224,0:3091,3634|226,0:1047,1572|227,0:1398,1940|231,0:954|233,0:302|249,0:1523,1638,1820|252,0:4757,4963|254,0:496|257,0:265,344|258,0:1028|259,0:172|260,0:360|261,128:13,131,483,509,3157|264,0:1521,1595|307,0:426,467|337,0:1370|338,0:452,2015|374,0:684|377,0:727,924|382,0:239|383,0:862|384,0:283,370,519,1005,1233,1594|391,0:303,558,683,923,1143|402,0:952|403,0:999|406,0:248|407,0:2425,2559,2683,2839|411,0:249|417,0:432,502,755,897|423,0:481,1344|424,0:1213|428,0:2351|442,0:894|445,0:331,339,964,1152,1750,1935,3729,4138,4270,5712|451,0:1852,2028|452,0:237,410,426,483,611,654,802,1027|453,0:681,1932|460,0:836|516,0:244|517,0:714|519,0:3758|529,0:631|531,0:316,1153|533,0:882|534,0:2603|535,0:969,1401,5109,6917,7218,7246,7469|536,0:9832,16925,19416,20763|537,4:228,356,382,412,523,534,540,555,2466|538,0:244|539,0:24950,25065,25247,30409,41562,41768,49580,72258|546,0:14575|549,0:1100,1704,2637,4875,5219,5256,5295,5380|550,0:4591,6390,6983,7324,7444,8903,14246,15273,16998,17024,17092,17172,17189,17296,18615,19221,19244,19529,19573,24310,24422,24434,25348,27153,27961,28064,29271,29664,29679,30384,30496,30508,34168,36769,36872,38108,38501,38516,39251,39363,39375,41220,41266,41362,41410,45602,46161,46942,50192,50915,51611,56017,57946,58014,59001,59015,59023,73548,73893,74766,82606,82669,83014,83039,84538,91022,91085,91430,91455,92437,100191,102216,103163,110745,120726,120928,120932,121681,122753,122846,122907,123300,125440,127798,127813,128080,129238,129315,133765,137662,139445,140301,140685,145163,145277,146916,148165,148345,148876,150105,159479,162241,162276,162345,163299,163343,163369,163466,163543,165256,166901,170223,170643,170676,170795,170845,170867,171087,171175,171222,171282,173702,173745,178892,180308,180335,180934,181054,181388,182221,183947,184232,214660,219637,222692,224654,226661,226719,226752,226789,227519,227746,228216,228229,228252,228336,228477,228499,228843,228901,228934,228971,230023,232538,236207,236953,237520,237548,237603,237705,237729,237770,237807,238058,238155,238203,238247,238853,238867,238980,238992,239093,239105,239208,239233,239237,239331,239340,240740,240763,240993,241012,241016,241352,241423,241479,241483,241851,241885,241889,241979,241983,242080,242084,242725,244872,245010,245032,245074,245078,245108,245155,245159,245242,245300,245347,245360,245404,245408,245441,245486,245490,245573,245617,245621,245654,245698,245702,245735,245786,245790,245830,245878,245882,245925,245975,245979,246008,246052,246056,246088,246136,246140,246409,246413,246475,246479,246518,246522,246573,246577,250754,250870,251551,251933,252078,252165,253294,253760,253842,254071,254147,254301,254403,254571,254759,254913,254977,256575,258015,258171,258227,259309,259472,259617,259828,260015,260305,260371,260508,260555,260869,260931,260980,261506,261646,261789,262143,262596,262766,263130,263343,263385,263420,263530,263678,264895,264919,264994,265069,265160,265489,266112,266345,266363,266550,266640,266909,267349,267411,267506,267650,267835,268007,268311,268521,268589,268967,269693,269882,270084,270224,270436,270786,271129,271196,271224,271279,271442,271622,272306,272443,272653,273425,273498,273599,274670,274867,275015,276222,277327,277357,278366,279236,279266,280443,280537,281299,281345,281491,281816,281934,282583,284226,284977,285023,285169,285394,285512,290592,290606,290619,290753,290936,291111,291162,291242,291376,291514,292363,292489,292748,292856,293034,293117,293434,295991,296028,296394,296405,297133,297575,297622,297841,298602,298664,298769,298903,299076,299341,299588,299831,299915,299932,299938,299954,300206,300270,300299,300317,300592,301920,302045,302115,302225,302609,302734,302818,302853,302870,302876,302892,302923,303043,303122,303151,303388,304821,307054,307721,308045,308560,308710,310318,311505,311758,312328,312521,312562,312653,316662,316758,320795,320923,321877,322502,328541,330263,330490,332712,332939,335228,338558,346604,346631,346655,346704,346827,346863,346986,347110,347229,347360,347746,347752,347756,347760,347803,347962,348009,370614,386569,389777,389901,392189,393293,393451,396645,397231,397245,398222,399448,399707,400546,400825,400899,406512,407672,407951,408025,409247,410261,411569,411848,411922,417189|551,0:39,375,1539,1568,3767,4792,6515,6541,6609,6689,6706,6813,8132,8738,8761,10997,11686,12517,13508,13606,13706,13829,14159,14937,14969,14981,15003,15607,15676,15688,15752,15881,15899,16008,16237,16257,16444,16473,17343,17935,17961,18453,18479,19075,19533,19628,20525,28788,29929,33691,35417,35611,35851,36486,37105,37199,37275,37533,37627,37703,38043,38413,38463,38656,38746,39205,39348,39566,39660,39738,39893,40180,40308,40386,40541,40724,40839,40856,40932,41080,41371,41459,41687,41781,42002,43557,43585,43769,43879,44046,44079,44119,44311,44435,44496,44520,44725,44754,44918,44998,45025,45068,45208,45217,45370,45644,45702,45854,46028,46080,46402|552,0:3384,3757,3886,4214,4399,4499,4526,4956,4998,5022,5065,5256,5279,5307,5333,5401,5427,5680,5817,5873,5970,6188,7122,7145,7341,19984,20327,20463,20694,20770,20901,20932,21029,21055,21419,21500,22047,22276,29439,37732,37907,37952,37985,38003,38263,38561,38748,38810,38893,38923,38975,39099,39140,39362,39507,39529,39634,39724,40175,40196,40331,40471,40537,42589,42701,43199,43296,43628,43731,48030,48311,48649,52210,55366,55572,60241,62299,62698,62907,67126,68928,68985,69146,69269"/></pk>
