<?xml version='1.0' encoding='utf-8' ?>
<!-- saved from url=(0014)about:internet -->
<ftswdata>
<key name="specific"> 304,307,311,32,386,298,265,278,82,279,370,318,17,5,314,21,205,200,207,208,235,238,18,19,188,20,283,290,210,25,26,199,262,247,285,227,211,133,266,338,39,327,27,374,148,359,383,379,179,37,275,157,62,343,223,225,248,390,138,226,56,57,59,60,75,173,372,134,287,216,229,168,44,231,140,142,143,169,106,297,218,391,321,300,47,49,51,52,54,55,129, </key>
<key name="specifical"> 200,207,208,254,227,137,302,214,138,56,57,59,60,142,143,106,325,391, </key>
<key name="specification"> 23,227,43,201,157, </key>
<key name="specify"> 307,32,145,2,30,340,243,244,272,268,239,247,256,252,253,254,285,211,186,264,223,225,213,56,57,59,60,277,372,134,139,215,229,168,44,295,297,391,144, </key>
<key name="speed"> 237,389, </key>
<key name="spent"> 43, </key>
<key name="spin"> 56, </key>
<key name="split"> 238,258,27,383,345, </key>
<key name="spoof"> 342, </key>
<key name="spool"> 200,2,183,61,369,168,142,143, </key>
<key name="sporadic"> 273, </key>
<key name="sportst"> 168, </key>
<key name="spr"> 22,35,36,38,40, </key>
<key name="spread"> 391, </key>
<key name="spreadsheet"> 205,208, </key>
<key name="springframework"> 38, </key>
<key name="spuriou"> 250,56,391, </key>
<key name="sql"> 82,200,195,196,197,198,23,25,39,41,327,181,158,72,79,85,86,203,169,204,126, </key>
<key name="sqlbrows"> 72,126, </key>
<key name="sqlserver:buf"> 79, </key>
<key name="sqlserver:databas"> 79, </key>
<key name="sqlserver:latch"> 79, </key>
<key name="sqlserver:lock"> 79, </key>
<key name="sqlserver:memory"> 79, </key>
<key name="sqlserveragent"> 72, </key>
<key name="src"> 35,9,176, </key>
<key name="ssh"> 82,340,342,61,62,64,57,65,66,67,68,69,70,71,72,73,74,76,77,78,79,81,85,84,203,87,88,89,90,91,93,94,95,96,98,99,100,101,102,103,104,105,106,107,108,109,110,111,112,113,391,92,392,204,115,116,117,118,119,120,121,122,123,124,125,126,127,128,130,131,132, </key>
<key name="ssh_apach"> 101, </key>
<key name="ssh_disk"> 112, </key>
<key name="ssh_disk_"> 283, </key>
<key name="ssh_disk_root"> 254,112, </key>
<key name="ssh_ldap"> 377, </key>
<key name="ssh_load"> 112, </key>
<key name="ssh_mailq_sendmail"> 111, </key>
<key name="ssh_memory"> 112, </key>
<key name="ssh_mysql_databas"> 107, </key>
<key name="ssh_mysql_engin"> 107, </key>
<key name="ssh_nmon_cpu"> 109, </key>
<key name="ssh_nmon_diskio"> 109, </key>
<key name="ssh_nmon_memory"> 109, </key>
<key name="ssh_nmon_pag"> 109, </key>
<key name="ssh_proces"> 102,103,104,105,107,108,111, </key>
<key name="ssh_process_cmd"> 104, </key>
<key name="ssh_process_count"> 112, </key>
<key name="ssh_process_crond"> 111, </key>
<key name="ssh_process_mysqld"> 107, </key>
<key name="ssh_process_mysqld_saf"> 107, </key>
<key name="ssh_process_nam"> 102,108, </key>
<key name="ssh_process_proftpd"> 103, </key>
<key name="ssh_process_sendmail_accept"> 111, </key>
<key name="ssh_process_sendmail_qrun"> 111, </key>
<key name="ssh_process_slapd"> 105, </key>
<key name="ssh_process_xinetd"> 111, </key>
<key name="ssh_sendmail"> 377, </key>
<key name="ssh_sendmaili"> 377, </key>
<key name="ssh_swap"> 112, </key>
<key name="ssh_unix"> 83, </key>
<key name="sshd"> 106, </key>
<key name="sshd_config"> 106, </key>
<key name="ssl"> 82,186,201,71,73,74,377,88,101,111,392,124,128, </key>
<key name="ssl_request_log"> 201, </key>
<key name="ssloption"> 186, </key>
<key name="sslrequir"> 186, </key>
<key name="sslrequiressl"> 186, </key>
<key name="sso"> 44, </key>
<key name="sso_"> 44, </key>
<key name="sso_createauthticket"> 44, </key>
<key name="stabl"> 165,391, </key>
<key name="stack"> 362,333,43,363,364,391, </key>
<key name="staff"> 318,264,390,391, </key>
<key name="stag"> 258, </key>
<key name="stalk"> 199, </key>
<key name="stamp"> 185,276, </key>
<key name="stand"> 258,248,93,100,151, </key>
<key name="standalon"> 386,201,180,59,163,391, </key>
<key name="standard"> 250,355,82,46,314,18,19,341,283,273,258,259,285,27,201,157,61,343,248,390,226,57,150,85,277,168,44,93,141,100,110,328,325,391,151, </key>
<key name="standardiz"> 57, </key>
<key name="standpoint"> 318, </key>
<key name="start"> 32,386,331,135,282,4,206,205,200,217,195,196,197,198,2,235,238,30,23,24,45,341,340,243,244,272,42,280,332,290,273,25,199,326,247,256,258,232,36,211,349,350,351,352,353,338,41,374,365,388,201,10,334,335,336,379,179,180,181,184,274,275,347,223,224,159,138,56,57,59,60,70,173,372,134,287,369,203,228,230,168,90,344,140,99,109,337,330,328,293,325,295,113,391,40,392,144,300,204,385,151,123, </key>
<key name="start_nmon"> 109, </key>
<key name="startdat"> 330, </key>
<key name="starter"> 391,151, </key>
<key name="startproc"> 168, </key>
<key name="startup"> 23,186,201,56,57,59,60,168,94,140,328, </key>
<key name="startup_messag"> 201, </key>
<key name="stastic"> 330, </key>
<key name="stat"> 265,135,267,370,318,333,196,198,382,2,243,244,42,199,247,256,252,253,254,211,186,316,147,327,27,374,375,201,292,383,176,184,390,376,367,56,57,59,60,150,377,372,168,44,94,99,330,360,297,391,378,144,127, </key>
<key name="stat_host_status_down"> 327, </key>
<key name="stat_host_status_pend"> 327, </key>
<key name="stat_host_status_unreachabl"> 327, </key>
<key name="stat_host_status_up"> 327, </key>
<key name="stat_service_status_critical"> 327, </key>
<key name="stat_service_status_ok"> 327, </key>
<key name="stat_service_status_pend"> 327, </key>
<key name="stat_service_status_unknown"> 327, </key>
<key name="stat_service_status_warn"> 327, </key>
<key name="state_typ"> 327, </key>
<key name="statechang"> 327, </key>
<key name="stateduration"> 330, </key>
<key name="stateles"> 226, </key>
<key name="statement"> 196,198,25,41,201,180,213,214,215,90,44,101, </key>
<key name="statetransitioncriteria"> 23, </key>
<key name="statetyp"> 23,26,327, </key>
<key name="statetypeid"> 327, </key>
<key name="statgen"> 99, </key>
<key name="static"> 374,57,60, </key>
<key name="station"> 59,141,142,169, </key>
<key name="statistic"> 361,16,327,374,375,379,380,376,56,59,377,354,90,93,94,95,96,141,100,101,106,109,330,373,325,378,323,55,127, </key>
<key name="statistical"> 332,327,369,330, </key>
<key name="statistictyp"> 330, </key>
<key name="statu"> 303,298,250,313,355,1,265,135,260,279,282,370,318,4,145,17,362,314,200,333,34,382,2,30,23,24,271,45,272,290,269,25,26,258,252,253,254,16,339,189,264,327,27,137,374,388,375,148,201,389,357,292,358,359,383,379,380,371,184,156,83,61,3,390,376,138,263,56,57,363,377,28,277,372,369,228,168,381,90,344,95,96,142,100,169,101,330,14,360,373,297,146,276,391,378,384,323,392,300,55,115,116,117,118,119,120,121,122,123,124,125,126,127,128,129,131,132, </key>
<key name="status"> 17,327, </key>
<key name="status'"> 370, </key>
<key name="status_fil"> 201, </key>
<key name="status_update_interval"> 201, </key>
<key name="statusmap"> 260,264, </key>
<key name="statuswrl"> 260,264, </key>
<key name="stay"> 377, </key>
<key name="stderr"> 201,391, </key>
<key name="stdout"> 201,29,134,391, </key>
<key name="stdout_enabl"> 201, </key>
<key name="steady"> 354, </key>
<key name="step"> 32,331,282,145,5,200,33,195,196,197,198,382,235,240,18,23,257,283,272,42,192,332,35,290,299,25,239,256,258,259,186,133,264,356,176,274,275,83,202,3,190,248,138,160,56,57,59,60,372,369,203,215,168,284,344,44,96,100,101,106,328,293,294,325,295,329,296,297,276,40,204,115,116,117,118,119,120,121,122,123,124,125,127,128,131, </key>
<key name="sth"> 176, </key>
<key name="still"> 1,256,258,259,133,43,263,80,134,203,228,106,391,144, </key>
<key name="stock"> 163, </key>
<key name="stop"> 250,200,195,196,197,198,2,23,24,243,244,199,41,201,10,180,181,184,56,57,59,60,65,66,67,68,69,70,71,72,73,74,76,77,173,372,203,168,344,392,204,117,118,120,121,122,123,124,126,128,130,131,132, </key>
<key name="stor"> 32,265,278,260,279,370,46,21,207,22,2,235,30,23,24,340,42,269,25,26,199,262,239,258,227,222,211,338,41,327,27,137,43,201,83,61,62,64,343,213,390,158,160,226,56,57,59,60,65,66,67,68,69,70,71,72,73,74,76,77,150,78,79,81,85,13,354,29,139,203,167,215,229,230,87,88,89,90,91,44,93,94,95,96,140,141,142,143,98,99,100,101,102,103,104,105,106,107,108,109,111,112,328,113,276,391,92,50,204,115,116,117,118,119,120,121,122,123,124,125,126,127,128,130,131,132, </key>
<key name="storag"> 267,4,200,43,95,391,132, </key>
<key name="storm"> 390, </key>
<key name="str"> 32,271,272,42,210,258,227,133,264,327,38,201,274,61,62,64,213,214,226,56,57,59,65,66,67,68,69,70,71,72,73,74,76,77,78,79,81,85,28,134,168,87,88,89,90,91,44,93,94,231,95,96,141,99,100,101,102,103,104,105,107,108,109,111,112,330,276,92,345,55,151,117,118,120,121,122,123,124,125,126,128,131,132, </key>
<key name="straightforward"> 217,232,56, </key>
<key name="strategi"> 200,202, </key>
<key name="strategy"> 200, </key>
<key name="stream"> 32,318,21,22,35,25,201,56,40, </key>
<key name="streamlin"> 56, </key>
<key name="strict"> 176,230,141,106, </key>
<key name="strictrequir"> 186, </key>
<key name="stricttap"> 168, </key>
<key name="string"> 145,272,133,226,57,150,277,231,106,151, </key>
<key name="strip"> 150, </key>
<key name="strong"> 264, </key>
<key name="structur"> 303,305,234,331,1,145,17,6,205,207,7,235,340,42,8,16,9,41,43,10,11,213,214,12,13,142,143,14,328,391,15, </key>
<key name="struggl"> 141, </key>
<key name="studio"> 46, </key>
<key name="styl"> 290,349,350,9, </key>
<key name="stylesheet"> 9, </key>
<key name="su"> 342,56,57,106, </key>
<key name="sub"> 303,298,318,2,340,258,291,201,292,176,302,191,213,59,187,293,218,300, </key>
<key name="subcomponent"> 30,26,327,176,37, </key>
<key name="subdirectory"> 264,3,60,106,151, </key>
<key name="subject"> 386,201,228, </key>
<key name="submit"> 314,382,18,192,25,133,201,190,191,193,372,168,391, </key>
<key name="subnet"> 250,222,223,390,56,59, </key>
<key name="subordinat"> 137,213,138,139,215,143,391, </key>
<key name="subroutin"> 258, </key>
<key name="subscription"> 154,155,84, </key>

</ftswdata>  
